mkpy3/__init__.py
mkpy3/check_mkpy3_v6.py
mkpy3/mkpy3_bad_radec_bug_v1.py
mkpy3/mkpy3_finder_chart_image_show_v1.py
mkpy3/mkpy3_finder_chart_survey_fits_image_get_v1.py
mkpy3/mkpy3_finder_chart_tpf_overlay_v6.py
mkpy3/mkpy3_plot_add_compass_rose_v5.py
mkpy3/mkpy3_tess_tpf_overlay_v6.py
mkpy3/mkpy3_tpf_get_coordinates_v1.py
mkpy3/mkpy3_tpf_overlay_v6.py
mkpy3/mkpy3_util.py
mkpy3/mkpy3_vizier_catalog_cone_get_v4.py
mkpy3/mkpy3_vizier_gaia_dr2_cone_get_v2.py
mkpy3/mkpy3_vizier_vsx_cone_get_v2.py
mkpy3/version.py
mkpy3/xmkpy3_k2_tpf_overlay_v2.py
mkpy3/xmkpy3_kepler_tpf_overlay_v2.py
mkpy3-1.0.1b21.dist-info/LICENSE
mkpy3-1.0.1b21.dist-info/METADATA
mkpy3-1.0.1b21.dist-info/WHEEL
mkpy3-1.0.1b21.dist-info/top_level.txt
mkpy3-1.0.1b21.dist-info/RECORD
