Metadata-Version: 2.1
Name: mkpy3
Version: 1.0.1b21
Summary: Python3 tools for the NASA TESS/K2/KEPLER astrophysical missions
Home-page: http://github.com/KenMighell/mkpy3
Author: Kenneth Mighell
Author-email: kmighell@seti.org
License: MIT
Platform: UNKNOWN
Classifier: Development Status :: 4 - Beta
Classifier: License :: OSI Approved :: MIT License
Classifier: Operating System :: OS Independent
Classifier: Programming Language :: Python
Classifier: Intended Audience :: Science/Research
Classifier: Topic :: Scientific/Engineering :: Astronomy
Requires-Python: >=3.6
